{
  "name": "extension",
  "description": "",
  "collectionOf": null,
  "isComplexType": false,
  "isEntitySet": false,
  "isOpenType": false,
  "allowPatch": true,
  "allowUpsert": true,
  "allowPatchCreate": true,
  "allowDelete": true,
  "isReferenceable": true,
  "isExpandable": true,
  "isFilterable": true,
  "isCountable": true,
  "isSelectable": true,
  "isSkipSupported": true,
  "isTopSupported": true,
  "info": null,
  "propertyNotes": "",
  "relationshipNotes": "",
  "methodNotes": "",
  "listDescription": "",
  "createDescription": "",
  "updateDescription": "",
  "deleteDescription": "",
  "restPath": {
    "/groups/<id>/threads/<id>/posts/<id>/extensions/<id>": true,
    "/groups/<id>/calendar/events/<id>/extensions/<id>": true,
    "/groups/<id>/calendar/calendarView/<id>/extensions/<id>": true,
    "/groups/<id>/calendarView/<id>/extensions/<id>": true,
    "/groups/<id>/events/<id>/extensions/<id>": true,
    "/groups/<id>/conversations/<id>/threads/<id>/posts/<id>/extensions/<id>": true,
    "/groups/<id>/drive/items/<id>/createdByUser/messages/<id>/extensions/<id>": true,
    "/groups/<id>/drive/items/<id>/createdByUser/mailFolders/<id>/messages/<id>/extensions/<id>": true,
    "/groups/<id>/drive/items/<id>/createdByUser/calendar/events/<id>/extensions/<id>": true,
    "/groups/<id>/drive/items/<id>/createdByUser/calendar/calendarView/<id>/extensions/<id>": true,
    "/groups/<id>/drive/items/<id>/createdByUser/calendarView/<id>/extensions/<id>": true,
    "/groups/<id>/drive/items/<id>/createdByUser/events/<id>/extensions/<id>": true,
    "/groups/<id>/drive/items/<id>/createdByUser/contacts/<id>/extensions/<id>": true,
    "/groups/<id>/drive/items/<id>/createdByUser/contactFolders/<id>/contacts/<id>/extensions/<id>": true,
    "/groups/<id>/drive/items/<id>/lastModifiedByUser/messages/<id>/extensions/<id>": true,
    "/groups/<id>/drive/items/<id>/lastModifiedByUser/mailFolders/<id>/messages/<id>/extensions/<id>": true,
    "/groups/<id>/drive/items/<id>/lastModifiedByUser/calendar/events/<id>/extensions/<id>": true,
    "/groups/<id>/drive/items/<id>/lastModifiedByUser/calendar/calendarView/<id>/extensions/<id>": true,
    "/groups/<id>/drive/items/<id>/lastModifiedByUser/calendarView/<id>/extensions/<id>": true,
    "/groups/<id>/drive/items/<id>/lastModifiedByUser/events/<id>/extensions/<id>": true,
    "/groups/<id>/drive/items/<id>/lastModifiedByUser/contacts/<id>/extensions/<id>": true,
    "/groups/<id>/drive/items/<id>/lastModifiedByUser/contactFolders/<id>/contacts/<id>/extensions/<id>": true,
    "/groups/<id>/drive/special/<id>/createdByUser/messages/<id>/extensions/<id>": true,
    "/groups/<id>/drive/special/<id>/createdByUser/mailFolders/<id>/messages/<id>/extensions/<id>": true,
    "/groups/<id>/drive/special/<id>/createdByUser/calendar/events/<id>/extensions/<id>": true,
    "/groups/<id>/drive/special/<id>/createdByUser/calendar/calendarView/<id>/extensions/<id>": true,
    "/groups/<id>/drive/special/<id>/createdByUser/calendarView/<id>/extensions/<id>": true,
    "/groups/<id>/drive/special/<id>/createdByUser/events/<id>/extensions/<id>": true,
    "/groups/<id>/drive/special/<id>/createdByUser/contacts/<id>/extensions/<id>": true,
    "/groups/<id>/drive/special/<id>/createdByUser/contactFolders/<id>/contacts/<id>/extensions/<id>": true,
    "/groups/<id>/drive/special/<id>/lastModifiedByUser/messages/<id>/extensions/<id>": true,
    "/groups/<id>/drive/special/<id>/lastModifiedByUser/mailFolders/<id>/messages/<id>/extensions/<id>": true,
    "/groups/<id>/drive/special/<id>/lastModifiedByUser/calendar/events/<id>/extensions/<id>": true,
    "/groups/<id>/drive/special/<id>/lastModifiedByUser/calendar/calendarView/<id>/extensions/<id>": true,
    "/groups/<id>/drive/special/<id>/lastModifiedByUser/calendarView/<id>/extensions/<id>": true,
    "/groups/<id>/drive/special/<id>/lastModifiedByUser/events/<id>/extensions/<id>": true,
    "/groups/<id>/drive/special/<id>/lastModifiedByUser/contacts/<id>/extensions/<id>": true,
    "/groups/<id>/drive/special/<id>/lastModifiedByUser/contactFolders/<id>/contacts/<id>/extensions/<id>": true,
    "/groups/<id>/drive/root/createdByUser/messages/<id>/extensions/<id>": true,
    "/groups/<id>/drive/root/createdByUser/mailFolders/<id>/messages/<id>/extensions/<id>": true,
    "/groups/<id>/drive/root/createdByUser/calendar/events/<id>/extensions/<id>": true,
    "/groups/<id>/drive/root/createdByUser/calendar/calendarView/<id>/extensions/<id>": true,
    "/groups/<id>/drive/root/createdByUser/calendarView/<id>/extensions/<id>": true,
    "/groups/<id>/drive/root/createdByUser/events/<id>/extensions/<id>": true,
    "/groups/<id>/drive/root/createdByUser/contacts/<id>/extensions/<id>": true,
    "/groups/<id>/drive/root/createdByUser/contactFolders/<id>/contacts/<id>/extensions/<id>": true,
    "/groups/<id>/drive/root/lastModifiedByUser/messages/<id>/extensions/<id>": true,
    "/groups/<id>/drive/root/lastModifiedByUser/mailFolders/<id>/messages/<id>/extensions/<id>": true,
    "/groups/<id>/drive/root/lastModifiedByUser/calendar/events/<id>/extensions/<id>": true,
    "/groups/<id>/drive/root/lastModifiedByUser/calendar/calendarView/<id>/extensions/<id>": true,
    "/groups/<id>/drive/root/lastModifiedByUser/calendarView/<id>/extensions/<id>": true,
    "/groups/<id>/drive/root/lastModifiedByUser/events/<id>/extensions/<id>": true,
    "/groups/<id>/drive/root/lastModifiedByUser/contacts/<id>/extensions/<id>": true,
    "/groups/<id>/drive/root/lastModifiedByUser/contactFolders/<id>/contacts/<id>/extensions/<id>": true,
    "/users/<id>/messages/<id>/extensions/<id>": true,
    "/users/<id>/joinedGroups/<id>/threads/<id>/posts/<id>/extensions/<id>": true,
    "/users/<id>/joinedGroups/<id>/calendar/events/<id>/extensions/<id>": true,
    "/users/<id>/joinedGroups/<id>/calendar/calendarView/<id>/extensions/<id>": true,
    "/users/<id>/joinedGroups/<id>/calendarView/<id>/extensions/<id>": true,
    "/users/<id>/joinedGroups/<id>/events/<id>/extensions/<id>": true,
    "/users/<id>/joinedGroups/<id>/conversations/<id>/threads/<id>/posts/<id>/extensions/<id>": true,
    "/users/<id>/mailFolders/<id>/messages/<id>/extensions/<id>": true,
    "/users/<id>/calendar/events/<id>/extensions/<id>": true,
    "/users/<id>/calendar/calendarView/<id>/extensions/<id>": true,
    "/users/<id>/calendarView/<id>/extensions/<id>": true,
    "/users/<id>/events/<id>/extensions/<id>": true,
    "/users/<id>/contacts/<id>/extensions/<id>": true,
    "/users/<id>/contactFolders/<id>/contacts/<id>/extensions/<id>": true,
    "/drives/<id>/items/<id>/createdByUser/messages/<id>/extensions/<id>": true,
    "/drives/<id>/items/<id>/createdByUser/joinedGroups/<id>/threads/<id>/posts/<id>/extensions/<id>": true,
    "/drives/<id>/items/<id>/createdByUser/joinedGroups/<id>/calendar/events/<id>/extensions/<id>": true,
    "/drives/<id>/items/<id>/createdByUser/joinedGroups/<id>/calendar/calendarView/<id>/extensions/<id>": true,
    "/drives/<id>/items/<id>/createdByUser/joinedGroups/<id>/calendarView/<id>/extensions/<id>": true,
    "/drives/<id>/items/<id>/createdByUser/joinedGroups/<id>/events/<id>/extensions/<id>": true,
    "/drives/<id>/items/<id>/createdByUser/joinedGroups/<id>/conversations/<id>/threads/<id>/posts/<id>/extensions/<id>": true,
    "/drives/<id>/items/<id>/createdByUser/mailFolders/<id>/messages/<id>/extensions/<id>": true,
    "/drives/<id>/items/<id>/createdByUser/calendar/events/<id>/extensions/<id>": true,
    "/drives/<id>/items/<id>/createdByUser/calendar/calendarView/<id>/extensions/<id>": true,
    "/drives/<id>/items/<id>/createdByUser/calendarView/<id>/extensions/<id>": true,
    "/drives/<id>/items/<id>/createdByUser/events/<id>/extensions/<id>": true,
    "/drives/<id>/items/<id>/createdByUser/contacts/<id>/extensions/<id>": true,
    "/drives/<id>/items/<id>/createdByUser/contactFolders/<id>/contacts/<id>/extensions/<id>": true,
    "/drives/<id>/items/<id>/lastModifiedByUser/messages/<id>/extensions/<id>": true,
    "/drives/<id>/items/<id>/lastModifiedByUser/joinedGroups/<id>/threads/<id>/posts/<id>/extensions/<id>": true,
    "/drives/<id>/items/<id>/lastModifiedByUser/joinedGroups/<id>/calendar/events/<id>/extensions/<id>": true,
    "/drives/<id>/items/<id>/lastModifiedByUser/joinedGroups/<id>/calendar/calendarView/<id>/extensions/<id>": true,
    "/drives/<id>/items/<id>/lastModifiedByUser/joinedGroups/<id>/calendarView/<id>/extensions/<id>": true,
    "/drives/<id>/items/<id>/lastModifiedByUser/joinedGroups/<id>/events/<id>/extensions/<id>": true,
    "/drives/<id>/items/<id>/lastModifiedByUser/joinedGroups/<id>/conversations/<id>/threads/<id>/posts/<id>/extensions/<id>": true,
    "/drives/<id>/items/<id>/lastModifiedByUser/mailFolders/<id>/messages/<id>/extensions/<id>": true,
    "/drives/<id>/items/<id>/lastModifiedByUser/calendar/events/<id>/extensions/<id>": true,
    "/drives/<id>/items/<id>/lastModifiedByUser/calendar/calendarView/<id>/extensions/<id>": true,
    "/drives/<id>/items/<id>/lastModifiedByUser/calendarView/<id>/extensions/<id>": true,
    "/drives/<id>/items/<id>/lastModifiedByUser/events/<id>/extensions/<id>": true,
    "/drives/<id>/items/<id>/lastModifiedByUser/contacts/<id>/extensions/<id>": true,
    "/drives/<id>/items/<id>/lastModifiedByUser/contactFolders/<id>/contacts/<id>/extensions/<id>": true,
    "/drives/<id>/special/<id>/createdByUser/messages/<id>/extensions/<id>": true,
    "/drives/<id>/special/<id>/createdByUser/joinedGroups/<id>/threads/<id>/posts/<id>/extensions/<id>": true,
    "/drives/<id>/special/<id>/createdByUser/joinedGroups/<id>/calendar/events/<id>/extensions/<id>": true,
    "/drives/<id>/special/<id>/createdByUser/joinedGroups/<id>/calendar/calendarView/<id>/extensions/<id>": true,
    "/drives/<id>/special/<id>/createdByUser/joinedGroups/<id>/calendarView/<id>/extensions/<id>": true,
    "/drives/<id>/special/<id>/createdByUser/joinedGroups/<id>/events/<id>/extensions/<id>": true,
    "/drives/<id>/special/<id>/createdByUser/joinedGroups/<id>/conversations/<id>/threads/<id>/posts/<id>/extensions/<id>": true,
    "/drives/<id>/special/<id>/createdByUser/mailFolders/<id>/messages/<id>/extensions/<id>": true,
    "/drives/<id>/special/<id>/createdByUser/calendar/events/<id>/extensions/<id>": true,
    "/drives/<id>/special/<id>/createdByUser/calendar/calendarView/<id>/extensions/<id>": true,
    "/drives/<id>/special/<id>/createdByUser/calendarView/<id>/extensions/<id>": true,
    "/drives/<id>/special/<id>/createdByUser/events/<id>/extensions/<id>": true,
    "/drives/<id>/special/<id>/createdByUser/contacts/<id>/extensions/<id>": true,
    "/drives/<id>/special/<id>/createdByUser/contactFolders/<id>/contacts/<id>/extensions/<id>": true,
    "/drives/<id>/special/<id>/lastModifiedByUser/messages/<id>/extensions/<id>": true,
    "/drives/<id>/special/<id>/lastModifiedByUser/joinedGroups/<id>/threads/<id>/posts/<id>/extensions/<id>": true,
    "/drives/<id>/special/<id>/lastModifiedByUser/joinedGroups/<id>/calendar/events/<id>/extensions/<id>": true,
    "/drives/<id>/special/<id>/lastModifiedByUser/joinedGroups/<id>/calendar/calendarView/<id>/extensions/<id>": true,
    "/drives/<id>/special/<id>/lastModifiedByUser/joinedGroups/<id>/calendarView/<id>/extensions/<id>": true,
    "/drives/<id>/special/<id>/lastModifiedByUser/joinedGroups/<id>/events/<id>/extensions/<id>": true,
    "/drives/<id>/special/<id>/lastModifiedByUser/joinedGroups/<id>/conversations/<id>/threads/<id>/posts/<id>/extensions/<id>": true,
    "/drives/<id>/special/<id>/lastModifiedByUser/mailFolders/<id>/messages/<id>/extensions/<id>": true,
    "/drives/<id>/special/<id>/lastModifiedByUser/calendar/events/<id>/extensions/<id>": true,
    "/drives/<id>/special/<id>/lastModifiedByUser/calendar/calendarView/<id>/extensions/<id>": true,
    "/drives/<id>/special/<id>/lastModifiedByUser/calendarView/<id>/extensions/<id>": true,
    "/drives/<id>/special/<id>/lastModifiedByUser/events/<id>/extensions/<id>": true,
    "/drives/<id>/special/<id>/lastModifiedByUser/contacts/<id>/extensions/<id>": true,
    "/drives/<id>/special/<id>/lastModifiedByUser/contactFolders/<id>/contacts/<id>/extensions/<id>": true,
    "/drives/<id>/root/createdByUser/messages/<id>/extensions/<id>": true,
    "/drives/<id>/root/createdByUser/joinedGroups/<id>/threads/<id>/posts/<id>/extensions/<id>": true,
    "/drives/<id>/root/createdByUser/joinedGroups/<id>/calendar/events/<id>/extensions/<id>": true,
    "/drives/<id>/root/createdByUser/joinedGroups/<id>/calendar/calendarView/<id>/extensions/<id>": true,
    "/drives/<id>/root/createdByUser/joinedGroups/<id>/calendarView/<id>/extensions/<id>": true,
    "/drives/<id>/root/createdByUser/joinedGroups/<id>/events/<id>/extensions/<id>": true,
    "/drives/<id>/root/createdByUser/joinedGroups/<id>/conversations/<id>/threads/<id>/posts/<id>/extensions/<id>": true,
    "/drives/<id>/root/createdByUser/mailFolders/<id>/messages/<id>/extensions/<id>": true,
    "/drives/<id>/root/createdByUser/calendar/events/<id>/extensions/<id>": true,
    "/drives/<id>/root/createdByUser/calendar/calendarView/<id>/extensions/<id>": true,
    "/drives/<id>/root/createdByUser/calendarView/<id>/extensions/<id>": true,
    "/drives/<id>/root/createdByUser/events/<id>/extensions/<id>": true,
    "/drives/<id>/root/createdByUser/contacts/<id>/extensions/<id>": true,
    "/drives/<id>/root/createdByUser/contactFolders/<id>/contacts/<id>/extensions/<id>": true,
    "/drives/<id>/root/lastModifiedByUser/messages/<id>/extensions/<id>": true,
    "/drives/<id>/root/lastModifiedByUser/joinedGroups/<id>/threads/<id>/posts/<id>/extensions/<id>": true,
    "/drives/<id>/root/lastModifiedByUser/joinedGroups/<id>/calendar/events/<id>/extensions/<id>": true,
    "/drives/<id>/root/lastModifiedByUser/joinedGroups/<id>/calendar/calendarView/<id>/extensions/<id>": true,
    "/drives/<id>/root/lastModifiedByUser/joinedGroups/<id>/calendarView/<id>/extensions/<id>": true,
    "/drives/<id>/root/lastModifiedByUser/joinedGroups/<id>/events/<id>/extensions/<id>": true,
    "/drives/<id>/root/lastModifiedByUser/joinedGroups/<id>/conversations/<id>/threads/<id>/posts/<id>/extensions/<id>": true,
    "/drives/<id>/root/lastModifiedByUser/mailFolders/<id>/messages/<id>/extensions/<id>": true,
    "/drives/<id>/root/lastModifiedByUser/calendar/events/<id>/extensions/<id>": true,
    "/drives/<id>/root/lastModifiedByUser/calendar/calendarView/<id>/extensions/<id>": true,
    "/drives/<id>/root/lastModifiedByUser/calendarView/<id>/extensions/<id>": true,
    "/drives/<id>/root/lastModifiedByUser/events/<id>/extensions/<id>": true,
    "/drives/<id>/root/lastModifiedByUser/contacts/<id>/extensions/<id>": true,
    "/drives/<id>/root/lastModifiedByUser/contactFolders/<id>/contacts/<id>/extensions/<id>": true,
    "/workbooks/<id>/createdByUser/messages/<id>/extensions/<id>": true,
    "/workbooks/<id>/createdByUser/joinedGroups/<id>/threads/<id>/posts/<id>/extensions/<id>": true,
    "/workbooks/<id>/createdByUser/joinedGroups/<id>/calendar/events/<id>/extensions/<id>": true,
    "/workbooks/<id>/createdByUser/joinedGroups/<id>/calendar/calendarView/<id>/extensions/<id>": true,
    "/workbooks/<id>/createdByUser/joinedGroups/<id>/calendarView/<id>/extensions/<id>": true,
    "/workbooks/<id>/createdByUser/joinedGroups/<id>/events/<id>/extensions/<id>": true,
    "/workbooks/<id>/createdByUser/joinedGroups/<id>/conversations/<id>/threads/<id>/posts/<id>/extensions/<id>": true,
    "/workbooks/<id>/createdByUser/mailFolders/<id>/messages/<id>/extensions/<id>": true,
    "/workbooks/<id>/createdByUser/calendar/events/<id>/extensions/<id>": true,
    "/workbooks/<id>/createdByUser/calendar/calendarView/<id>/extensions/<id>": true,
    "/workbooks/<id>/createdByUser/calendarView/<id>/extensions/<id>": true,
    "/workbooks/<id>/createdByUser/events/<id>/extensions/<id>": true,
    "/workbooks/<id>/createdByUser/contacts/<id>/extensions/<id>": true,
    "/workbooks/<id>/createdByUser/contactFolders/<id>/contacts/<id>/extensions/<id>": true,
    "/workbooks/<id>/lastModifiedByUser/messages/<id>/extensions/<id>": true,
    "/workbooks/<id>/lastModifiedByUser/joinedGroups/<id>/threads/<id>/posts/<id>/extensions/<id>": true,
    "/workbooks/<id>/lastModifiedByUser/joinedGroups/<id>/calendar/events/<id>/extensions/<id>": true,
    "/workbooks/<id>/lastModifiedByUser/joinedGroups/<id>/calendar/calendarView/<id>/extensions/<id>": true,
    "/workbooks/<id>/lastModifiedByUser/joinedGroups/<id>/calendarView/<id>/extensions/<id>": true,
    "/workbooks/<id>/lastModifiedByUser/joinedGroups/<id>/events/<id>/extensions/<id>": true,
    "/workbooks/<id>/lastModifiedByUser/joinedGroups/<id>/conversations/<id>/threads/<id>/posts/<id>/extensions/<id>": true,
    "/workbooks/<id>/lastModifiedByUser/mailFolders/<id>/messages/<id>/extensions/<id>": true,
    "/workbooks/<id>/lastModifiedByUser/calendar/events/<id>/extensions/<id>": true,
    "/workbooks/<id>/lastModifiedByUser/calendar/calendarView/<id>/extensions/<id>": true,
    "/workbooks/<id>/lastModifiedByUser/calendarView/<id>/extensions/<id>": true,
    "/workbooks/<id>/lastModifiedByUser/events/<id>/extensions/<id>": true,
    "/workbooks/<id>/lastModifiedByUser/contacts/<id>/extensions/<id>": true,
    "/workbooks/<id>/lastModifiedByUser/contactFolders/<id>/contacts/<id>/extensions/<id>": true,
    "/identityRiskEvents/<id>/impactedUser/messages/<id>/extensions/<id>": true,
    "/identityRiskEvents/<id>/impactedUser/joinedGroups/<id>/threads/<id>/posts/<id>/extensions/<id>": true,
    "/identityRiskEvents/<id>/impactedUser/joinedGroups/<id>/calendar/events/<id>/extensions/<id>": true,
    "/identityRiskEvents/<id>/impactedUser/joinedGroups/<id>/calendar/calendarView/<id>/extensions/<id>": true,
    "/identityRiskEvents/<id>/impactedUser/joinedGroups/<id>/calendarView/<id>/extensions/<id>": true,
    "/identityRiskEvents/<id>/impactedUser/joinedGroups/<id>/events/<id>/extensions/<id>": true,
    "/identityRiskEvents/<id>/impactedUser/joinedGroups/<id>/conversations/<id>/threads/<id>/posts/<id>/extensions/<id>": true,
    "/identityRiskEvents/<id>/impactedUser/mailFolders/<id>/messages/<id>/extensions/<id>": true,
    "/identityRiskEvents/<id>/impactedUser/calendar/events/<id>/extensions/<id>": true,
    "/identityRiskEvents/<id>/impactedUser/calendar/calendarView/<id>/extensions/<id>": true,
    "/identityRiskEvents/<id>/impactedUser/calendarView/<id>/extensions/<id>": true,
    "/identityRiskEvents/<id>/impactedUser/events/<id>/extensions/<id>": true,
    "/identityRiskEvents/<id>/impactedUser/contacts/<id>/extensions/<id>": true,
    "/identityRiskEvents/<id>/impactedUser/contactFolders/<id>/contacts/<id>/extensions/<id>": true,
    "/impossibleTravelRiskEvents/<id>/impactedUser/messages/<id>/extensions/<id>": true,
    "/impossibleTravelRiskEvents/<id>/impactedUser/joinedGroups/<id>/threads/<id>/posts/<id>/extensions/<id>": true,
    "/impossibleTravelRiskEvents/<id>/impactedUser/joinedGroups/<id>/calendar/events/<id>/extensions/<id>": true,
    "/impossibleTravelRiskEvents/<id>/impactedUser/joinedGroups/<id>/calendar/calendarView/<id>/extensions/<id>": true,
    "/impossibleTravelRiskEvents/<id>/impactedUser/joinedGroups/<id>/calendarView/<id>/extensions/<id>": true,
    "/impossibleTravelRiskEvents/<id>/impactedUser/joinedGroups/<id>/events/<id>/extensions/<id>": true,
    "/impossibleTravelRiskEvents/<id>/impactedUser/joinedGroups/<id>/conversations/<id>/threads/<id>/posts/<id>/extensions/<id>": true,
    "/impossibleTravelRiskEvents/<id>/impactedUser/mailFolders/<id>/messages/<id>/extensions/<id>": true,
    "/impossibleTravelRiskEvents/<id>/impactedUser/calendar/events/<id>/extensions/<id>": true,
    "/impossibleTravelRiskEvents/<id>/impactedUser/calendar/calendarView/<id>/extensions/<id>": true,
    "/impossibleTravelRiskEvents/<id>/impactedUser/calendarView/<id>/extensions/<id>": true,
    "/impossibleTravelRiskEvents/<id>/impactedUser/events/<id>/extensions/<id>": true,
    "/impossibleTravelRiskEvents/<id>/impactedUser/contacts/<id>/extensions/<id>": true,
    "/impossibleTravelRiskEvents/<id>/impactedUser/contactFolders/<id>/contacts/<id>/extensions/<id>": true,
    "/leakedCredentialsRiskEvents/<id>/impactedUser/messages/<id>/extensions/<id>": true,
    "/leakedCredentialsRiskEvents/<id>/impactedUser/joinedGroups/<id>/threads/<id>/posts/<id>/extensions/<id>": true,
    "/leakedCredentialsRiskEvents/<id>/impactedUser/joinedGroups/<id>/calendar/events/<id>/extensions/<id>": true,
    "/leakedCredentialsRiskEvents/<id>/impactedUser/joinedGroups/<id>/calendar/calendarView/<id>/extensions/<id>": true,
    "/leakedCredentialsRiskEvents/<id>/impactedUser/joinedGroups/<id>/calendarView/<id>/extensions/<id>": true,
    "/leakedCredentialsRiskEvents/<id>/impactedUser/joinedGroups/<id>/events/<id>/extensions/<id>": true,
    "/leakedCredentialsRiskEvents/<id>/impactedUser/joinedGroups/<id>/conversations/<id>/threads/<id>/posts/<id>/extensions/<id>": true,
    "/leakedCredentialsRiskEvents/<id>/impactedUser/mailFolders/<id>/messages/<id>/extensions/<id>": true,
    "/leakedCredentialsRiskEvents/<id>/impactedUser/calendar/events/<id>/extensions/<id>": true,
    "/leakedCredentialsRiskEvents/<id>/impactedUser/calendar/calendarView/<id>/extensions/<id>": true,
    "/leakedCredentialsRiskEvents/<id>/impactedUser/calendarView/<id>/extensions/<id>": true,
    "/leakedCredentialsRiskEvents/<id>/impactedUser/events/<id>/extensions/<id>": true,
    "/leakedCredentialsRiskEvents/<id>/impactedUser/contacts/<id>/extensions/<id>": true,
    "/leakedCredentialsRiskEvents/<id>/impactedUser/contactFolders/<id>/contacts/<id>/extensions/<id>": true,
    "/anonymousIpRiskEvents/<id>/impactedUser/messages/<id>/extensions/<id>": true,
    "/anonymousIpRiskEvents/<id>/impactedUser/joinedGroups/<id>/threads/<id>/posts/<id>/extensions/<id>": true,
    "/anonymousIpRiskEvents/<id>/impactedUser/joinedGroups/<id>/calendar/events/<id>/extensions/<id>": true,
    "/anonymousIpRiskEvents/<id>/impactedUser/joinedGroups/<id>/calendar/calendarView/<id>/extensions/<id>": true,
    "/anonymousIpRiskEvents/<id>/impactedUser/joinedGroups/<id>/calendarView/<id>/extensions/<id>": true,
    "/anonymousIpRiskEvents/<id>/impactedUser/joinedGroups/<id>/events/<id>/extensions/<id>": true,
    "/anonymousIpRiskEvents/<id>/impactedUser/joinedGroups/<id>/conversations/<id>/threads/<id>/posts/<id>/extensions/<id>": true,
    "/anonymousIpRiskEvents/<id>/impactedUser/mailFolders/<id>/messages/<id>/extensions/<id>": true,
    "/anonymousIpRiskEvents/<id>/impactedUser/calendar/events/<id>/extensions/<id>": true,
    "/anonymousIpRiskEvents/<id>/impactedUser/calendar/calendarView/<id>/extensions/<id>": true,
    "/anonymousIpRiskEvents/<id>/impactedUser/calendarView/<id>/extensions/<id>": true,
    "/anonymousIpRiskEvents/<id>/impactedUser/events/<id>/extensions/<id>": true,
    "/anonymousIpRiskEvents/<id>/impactedUser/contacts/<id>/extensions/<id>": true,
    "/anonymousIpRiskEvents/<id>/impactedUser/contactFolders/<id>/contacts/<id>/extensions/<id>": true,
    "/suspiciousIpRiskEvents/<id>/impactedUser/messages/<id>/extensions/<id>": true,
    "/suspiciousIpRiskEvents/<id>/impactedUser/joinedGroups/<id>/threads/<id>/posts/<id>/extensions/<id>": true,
    "/suspiciousIpRiskEvents/<id>/impactedUser/joinedGroups/<id>/calendar/events/<id>/extensions/<id>": true,
    "/suspiciousIpRiskEvents/<id>/impactedUser/joinedGroups/<id>/calendar/calendarView/<id>/extensions/<id>": true,
    "/suspiciousIpRiskEvents/<id>/impactedUser/joinedGroups/<id>/calendarView/<id>/extensions/<id>": true,
    "/suspiciousIpRiskEvents/<id>/impactedUser/joinedGroups/<id>/events/<id>/extensions/<id>": true,
    "/suspiciousIpRiskEvents/<id>/impactedUser/joinedGroups/<id>/conversations/<id>/threads/<id>/posts/<id>/extensions/<id>": true,
    "/suspiciousIpRiskEvents/<id>/impactedUser/mailFolders/<id>/messages/<id>/extensions/<id>": true,
    "/suspiciousIpRiskEvents/<id>/impactedUser/calendar/events/<id>/extensions/<id>": true,
    "/suspiciousIpRiskEvents/<id>/impactedUser/calendar/calendarView/<id>/extensions/<id>": true,
    "/suspiciousIpRiskEvents/<id>/impactedUser/calendarView/<id>/extensions/<id>": true,
    "/suspiciousIpRiskEvents/<id>/impactedUser/events/<id>/extensions/<id>": true,
    "/suspiciousIpRiskEvents/<id>/impactedUser/contacts/<id>/extensions/<id>": true,
    "/suspiciousIpRiskEvents/<id>/impactedUser/contactFolders/<id>/contacts/<id>/extensions/<id>": true,
    "/unfamiliarLocationRiskEvents/<id>/impactedUser/messages/<id>/extensions/<id>": true,
    "/unfamiliarLocationRiskEvents/<id>/impactedUser/joinedGroups/<id>/threads/<id>/posts/<id>/extensions/<id>": true,
    "/unfamiliarLocationRiskEvents/<id>/impactedUser/joinedGroups/<id>/calendar/events/<id>/extensions/<id>": true,
    "/unfamiliarLocationRiskEvents/<id>/impactedUser/joinedGroups/<id>/calendar/calendarView/<id>/extensions/<id>": true,
    "/unfamiliarLocationRiskEvents/<id>/impactedUser/joinedGroups/<id>/calendarView/<id>/extensions/<id>": true,
    "/unfamiliarLocationRiskEvents/<id>/impactedUser/joinedGroups/<id>/events/<id>/extensions/<id>": true,
    "/unfamiliarLocationRiskEvents/<id>/impactedUser/joinedGroups/<id>/conversations/<id>/threads/<id>/posts/<id>/extensions/<id>": true,
    "/unfamiliarLocationRiskEvents/<id>/impactedUser/mailFolders/<id>/messages/<id>/extensions/<id>": true,
    "/unfamiliarLocationRiskEvents/<id>/impactedUser/calendar/events/<id>/extensions/<id>": true,
    "/unfamiliarLocationRiskEvents/<id>/impactedUser/calendar/calendarView/<id>/extensions/<id>": true,
    "/unfamiliarLocationRiskEvents/<id>/impactedUser/calendarView/<id>/extensions/<id>": true,
    "/unfamiliarLocationRiskEvents/<id>/impactedUser/events/<id>/extensions/<id>": true,
    "/unfamiliarLocationRiskEvents/<id>/impactedUser/contacts/<id>/extensions/<id>": true,
    "/unfamiliarLocationRiskEvents/<id>/impactedUser/contactFolders/<id>/contacts/<id>/extensions/<id>": true,
    "/botnetRiskEvents/<id>/impactedUser/messages/<id>/extensions/<id>": true,
    "/botnetRiskEvents/<id>/impactedUser/joinedGroups/<id>/threads/<id>/posts/<id>/extensions/<id>": true,
    "/botnetRiskEvents/<id>/impactedUser/joinedGroups/<id>/calendar/events/<id>/extensions/<id>": true,
    "/botnetRiskEvents/<id>/impactedUser/joinedGroups/<id>/calendar/calendarView/<id>/extensions/<id>": true,
    "/botnetRiskEvents/<id>/impactedUser/joinedGroups/<id>/calendarView/<id>/extensions/<id>": true,
    "/botnetRiskEvents/<id>/impactedUser/joinedGroups/<id>/events/<id>/extensions/<id>": true,
    "/botnetRiskEvents/<id>/impactedUser/joinedGroups/<id>/conversations/<id>/threads/<id>/posts/<id>/extensions/<id>": true,
    "/botnetRiskEvents/<id>/impactedUser/mailFolders/<id>/messages/<id>/extensions/<id>": true,
    "/botnetRiskEvents/<id>/impactedUser/calendar/events/<id>/extensions/<id>": true,
    "/botnetRiskEvents/<id>/impactedUser/calendar/calendarView/<id>/extensions/<id>": true,
    "/botnetRiskEvents/<id>/impactedUser/calendarView/<id>/extensions/<id>": true,
    "/botnetRiskEvents/<id>/impactedUser/events/<id>/extensions/<id>": true,
    "/botnetRiskEvents/<id>/impactedUser/contacts/<id>/extensions/<id>": true,
    "/botnetRiskEvents/<id>/impactedUser/contactFolders/<id>/contacts/<id>/extensions/<id>": true,
    "/me/messages/<id>/extensions/<id>": true,
    "/me/joinedGroups/<id>/threads/<id>/posts/<id>/extensions/<id>": true,
    "/me/joinedGroups/<id>/calendar/events/<id>/extensions/<id>": true,
    "/me/joinedGroups/<id>/calendar/calendarView/<id>/extensions/<id>": true,
    "/me/joinedGroups/<id>/calendarView/<id>/extensions/<id>": true,
    "/me/joinedGroups/<id>/events/<id>/extensions/<id>": true,
    "/me/joinedGroups/<id>/conversations/<id>/threads/<id>/posts/<id>/extensions/<id>": true,
    "/me/mailFolders/<id>/messages/<id>/extensions/<id>": true,
    "/me/calendar/events/<id>/extensions/<id>": true,
    "/me/calendar/calendarView/<id>/extensions/<id>": true,
    "/me/calendarView/<id>/extensions/<id>": true,
    "/me/events/<id>/extensions/<id>": true,
    "/me/contacts/<id>/extensions/<id>": true,
    "/me/contactFolders/<id>/contacts/<id>/extensions/<id>": true,
    "/drive/items/<id>/createdByUser/messages/<id>/extensions/<id>": true,
    "/drive/items/<id>/createdByUser/joinedGroups/<id>/threads/<id>/posts/<id>/extensions/<id>": true,
    "/drive/items/<id>/createdByUser/joinedGroups/<id>/calendar/events/<id>/extensions/<id>": true,
    "/drive/items/<id>/createdByUser/joinedGroups/<id>/calendar/calendarView/<id>/extensions/<id>": true,
    "/drive/items/<id>/createdByUser/joinedGroups/<id>/calendarView/<id>/extensions/<id>": true,
    "/drive/items/<id>/createdByUser/joinedGroups/<id>/events/<id>/extensions/<id>": true,
    "/drive/items/<id>/createdByUser/joinedGroups/<id>/conversations/<id>/threads/<id>/posts/<id>/extensions/<id>": true,
    "/drive/items/<id>/createdByUser/mailFolders/<id>/messages/<id>/extensions/<id>": true,
    "/drive/items/<id>/createdByUser/calendar/events/<id>/extensions/<id>": true,
    "/drive/items/<id>/createdByUser/calendar/calendarView/<id>/extensions/<id>": true,
    "/drive/items/<id>/createdByUser/calendarView/<id>/extensions/<id>": true,
    "/drive/items/<id>/createdByUser/events/<id>/extensions/<id>": true,
    "/drive/items/<id>/createdByUser/contacts/<id>/extensions/<id>": true,
    "/drive/items/<id>/createdByUser/contactFolders/<id>/contacts/<id>/extensions/<id>": true,
    "/drive/items/<id>/lastModifiedByUser/messages/<id>/extensions/<id>": true,
    "/drive/items/<id>/lastModifiedByUser/joinedGroups/<id>/threads/<id>/posts/<id>/extensions/<id>": true,
    "/drive/items/<id>/lastModifiedByUser/joinedGroups/<id>/calendar/events/<id>/extensions/<id>": true,
    "/drive/items/<id>/lastModifiedByUser/joinedGroups/<id>/calendar/calendarView/<id>/extensions/<id>": true,
    "/drive/items/<id>/lastModifiedByUser/joinedGroups/<id>/calendarView/<id>/extensions/<id>": true,
    "/drive/items/<id>/lastModifiedByUser/joinedGroups/<id>/events/<id>/extensions/<id>": true,
    "/drive/items/<id>/lastModifiedByUser/joinedGroups/<id>/conversations/<id>/threads/<id>/posts/<id>/extensions/<id>": true,
    "/drive/items/<id>/lastModifiedByUser/mailFolders/<id>/messages/<id>/extensions/<id>": true,
    "/drive/items/<id>/lastModifiedByUser/calendar/events/<id>/extensions/<id>": true,
    "/drive/items/<id>/lastModifiedByUser/calendar/calendarView/<id>/extensions/<id>": true,
    "/drive/items/<id>/lastModifiedByUser/calendarView/<id>/extensions/<id>": true,
    "/drive/items/<id>/lastModifiedByUser/events/<id>/extensions/<id>": true,
    "/drive/items/<id>/lastModifiedByUser/contacts/<id>/extensions/<id>": true,
    "/drive/items/<id>/lastModifiedByUser/contactFolders/<id>/contacts/<id>/extensions/<id>": true,
    "/drive/special/<id>/createdByUser/messages/<id>/extensions/<id>": true,
    "/drive/special/<id>/createdByUser/joinedGroups/<id>/threads/<id>/posts/<id>/extensions/<id>": true,
    "/drive/special/<id>/createdByUser/joinedGroups/<id>/calendar/events/<id>/extensions/<id>": true,
    "/drive/special/<id>/createdByUser/joinedGroups/<id>/calendar/calendarView/<id>/extensions/<id>": true,
    "/drive/special/<id>/createdByUser/joinedGroups/<id>/calendarView/<id>/extensions/<id>": true,
    "/drive/special/<id>/createdByUser/joinedGroups/<id>/events/<id>/extensions/<id>": true,
    "/drive/special/<id>/createdByUser/joinedGroups/<id>/conversations/<id>/threads/<id>/posts/<id>/extensions/<id>": true,
    "/drive/special/<id>/createdByUser/mailFolders/<id>/messages/<id>/extensions/<id>": true,
    "/drive/special/<id>/createdByUser/calendar/events/<id>/extensions/<id>": true,
    "/drive/special/<id>/createdByUser/calendar/calendarView/<id>/extensions/<id>": true,
    "/drive/special/<id>/createdByUser/calendarView/<id>/extensions/<id>": true,
    "/drive/special/<id>/createdByUser/events/<id>/extensions/<id>": true,
    "/drive/special/<id>/createdByUser/contacts/<id>/extensions/<id>": true,
    "/drive/special/<id>/createdByUser/contactFolders/<id>/contacts/<id>/extensions/<id>": true,
    "/drive/special/<id>/lastModifiedByUser/messages/<id>/extensions/<id>": true,
    "/drive/special/<id>/lastModifiedByUser/joinedGroups/<id>/threads/<id>/posts/<id>/extensions/<id>": true,
    "/drive/special/<id>/lastModifiedByUser/joinedGroups/<id>/calendar/events/<id>/extensions/<id>": true,
    "/drive/special/<id>/lastModifiedByUser/joinedGroups/<id>/calendar/calendarView/<id>/extensions/<id>": true,
    "/drive/special/<id>/lastModifiedByUser/joinedGroups/<id>/calendarView/<id>/extensions/<id>": true,
    "/drive/special/<id>/lastModifiedByUser/joinedGroups/<id>/events/<id>/extensions/<id>": true,
    "/drive/special/<id>/lastModifiedByUser/joinedGroups/<id>/conversations/<id>/threads/<id>/posts/<id>/extensions/<id>": true,
    "/drive/special/<id>/lastModifiedByUser/mailFolders/<id>/messages/<id>/extensions/<id>": true,
    "/drive/special/<id>/lastModifiedByUser/calendar/events/<id>/extensions/<id>": true,
    "/drive/special/<id>/lastModifiedByUser/calendar/calendarView/<id>/extensions/<id>": true,
    "/drive/special/<id>/lastModifiedByUser/calendarView/<id>/extensions/<id>": true,
    "/drive/special/<id>/lastModifiedByUser/events/<id>/extensions/<id>": true,
    "/drive/special/<id>/lastModifiedByUser/contacts/<id>/extensions/<id>": true,
    "/drive/special/<id>/lastModifiedByUser/contactFolders/<id>/contacts/<id>/extensions/<id>": true,
    "/drive/root/createdByUser/messages/<id>/extensions/<id>": true,
    "/drive/root/createdByUser/joinedGroups/<id>/threads/<id>/posts/<id>/extensions/<id>": true,
    "/drive/root/createdByUser/joinedGroups/<id>/calendar/events/<id>/extensions/<id>": true,
    "/drive/root/createdByUser/joinedGroups/<id>/calendar/calendarView/<id>/extensions/<id>": true,
    "/drive/root/createdByUser/joinedGroups/<id>/calendarView/<id>/extensions/<id>": true,
    "/drive/root/createdByUser/joinedGroups/<id>/events/<id>/extensions/<id>": true,
    "/drive/root/createdByUser/joinedGroups/<id>/conversations/<id>/threads/<id>/posts/<id>/extensions/<id>": true,
    "/drive/root/createdByUser/mailFolders/<id>/messages/<id>/extensions/<id>": true,
    "/drive/root/createdByUser/calendar/events/<id>/extensions/<id>": true,
    "/drive/root/createdByUser/calendar/calendarView/<id>/extensions/<id>": true,
    "/drive/root/createdByUser/calendarView/<id>/extensions/<id>": true,
    "/drive/root/createdByUser/events/<id>/extensions/<id>": true,
    "/drive/root/createdByUser/contacts/<id>/extensions/<id>": true,
    "/drive/root/createdByUser/contactFolders/<id>/contacts/<id>/extensions/<id>": true,
    "/drive/root/lastModifiedByUser/messages/<id>/extensions/<id>": true,
    "/drive/root/lastModifiedByUser/joinedGroups/<id>/threads/<id>/posts/<id>/extensions/<id>": true,
    "/drive/root/lastModifiedByUser/joinedGroups/<id>/calendar/events/<id>/extensions/<id>": true,
    "/drive/root/lastModifiedByUser/joinedGroups/<id>/calendar/calendarView/<id>/extensions/<id>": true,
    "/drive/root/lastModifiedByUser/joinedGroups/<id>/calendarView/<id>/extensions/<id>": true,
    "/drive/root/lastModifiedByUser/joinedGroups/<id>/events/<id>/extensions/<id>": true,
    "/drive/root/lastModifiedByUser/joinedGroups/<id>/conversations/<id>/threads/<id>/posts/<id>/extensions/<id>": true,
    "/drive/root/lastModifiedByUser/mailFolders/<id>/messages/<id>/extensions/<id>": true,
    "/drive/root/lastModifiedByUser/calendar/events/<id>/extensions/<id>": true,
    "/drive/root/lastModifiedByUser/calendar/calendarView/<id>/extensions/<id>": true,
    "/drive/root/lastModifiedByUser/calendarView/<id>/extensions/<id>": true,
    "/drive/root/lastModifiedByUser/events/<id>/extensions/<id>": true,
    "/drive/root/lastModifiedByUser/contacts/<id>/extensions/<id>": true,
    "/drive/root/lastModifiedByUser/contactFolders/<id>/contacts/<id>/extensions/<id>": true
  },
  "properties": [
    {
      "name": "id",
      "description": "",
      "isKey": true,
      "dataType": "string",
      "isReadOnly": true,
      "enumName": null,
      "isCollection": false,
      "isRelationship": false,
      "supportFilter": false,
      "allowPostToCollection": true,
      "isNullable": false,
      "isUnicode": false
    }
  ],
  "methods": [

  ]
}