{
  "name": "PatternedRecurrence",
  "description": null,
  "collectionOf": null,
  "isComplexType": true,
  "isEntitySet": false,
  "allowPatch": false,
  "allowUpsert": false,
  "allowPatchCreate": false,
  "allowDelete": false,
  "restPath": [

  ],
  "info": null,
  "properties": [
    {
      "name": "Pattern",
      "isKey": false,
      "dataType": "RecurrencePattern",
      "description": null,
      "isReadOnly": false,
      "enumName": null,
      "isCollection": false,
      "isRelationship": false,
      "isNullable": true,
      "isUnicode": null
    },
    {
      "name": "Range",
      "isKey": false,
      "dataType": "RecurrenceRange",
      "description": null,
      "isReadOnly": false,
      "enumName": null,
      "isCollection": false,
      "isRelationship": false,
      "isNullable": true,
      "isUnicode": null
    }
  ],
  "methods": [

  ]
}