{
  "name": "RangeFill",
  "description": "Represents the background of a range object.",
  "collectionOf": null,
  "isComplexType": false,
  "isEntitySet": false,
  "allowPatch": true,
  "allowUpsert": true,
  "allowPatchCreate": true,
  "allowDelete": true,
  "isReferenceable": true,
  "isExpandable": true,
  "isFilterable": true,
  "isCountable": true,
  "isSelectable": true,
  "isSkipSupported": true,
  "isTopSupported": true,
  "info": null,
  "propertyNotes": "",
  "relationshipNotes": "",
  "methodNotes": "",
  "listDescription": "",
  "createDescription": "",
  "updateDescription": "",
  "deleteDescription": "",
  "restPath": {
  },
  "properties": [
    {
      "name": "color",
      "description": "HTML color code representing the color of the border line, of the form #RRGGBB (e.g. \"FFA500\") or as a named HTML color (e.g. \"orange\")",
      "isKey": null,
      "dataType": "string",
      "isReadOnly": false,
      "enumName": null,
      "isCollection": false,
      "isRelationship": false,
      "supportFilter": false,
      "allowPostToCollection": true,
      "isNullable": null,
      "isUnicode": null
    }
  ],
  "methods": [
    {
      "name": "clear",
      "displayName": "",
      "description": "Resets the range background.",
      "prerequisites": "",
      "returnType": null,
      "isReturnNullable": null,
      "isReturnTypeCollection": false,
      "httpSuccessCode": null,
      "isFunction": null,
      "scopes": [

      ],
      "errorCodes": [

      ],
      "parameters": [

      ]
    }
  ]
}