{
  "name": "MailFolder",
  "description": "",
  "collectionOf": null,
  "allowPostToCollection": null,
  "isComplexType": false,
  "isEntitySet": false,
  "allowPatch": true,
  "allowUpsert": true,
  "allowPatchCreate": true,
  "allowDelete": true,
  "restPath": [

  ],
  "info": null,
  "properties": [
    {
      "name": "ParentFolderId",
      "isKey": false,
      "dataType": "String",
      "description": "",
      "isReadOnly": false,
      "enumName": null,
      "isCollection": false,
      "isRelationship": false,
      "isNullable": true,
      "isUnicode": false
    },
    {
      "name": "DisplayName",
      "isKey": false,
      "dataType": "String",
      "description": "",
      "isReadOnly": false,
      "enumName": null,
      "isCollection": false,
      "isRelationship": false,
      "isNullable": true,
      "isUnicode": false
    },
    {
      "name": "ChildFolderCount",
      "isKey": false,
      "dataType": "Int32",
      "description": "",
      "isReadOnly": false,
      "enumName": null,
      "isCollection": false,
      "isRelationship": false,
      "isNullable": true,
      "isUnicode": null
    },
    {
      "name": "Id",
      "isKey": true,
      "dataType": "String",
      "description": "",
      "isReadOnly": true,
      "enumName": null,
      "isCollection": false,
      "isRelationship": false,
      "isNullable": false,
      "isUnicode": false
    },
    {
      "name": "ChildFolders",
      "isKey": false,
      "dataType": "MailFolder",
      "description": "",
      "isReadOnly": true,
      "enumName": null,
      "isCollection": true,
      "isRelationship": true,
      "isNullable": true,
      "isUnicode": null
    },
    {
      "name": "Messages",
      "isKey": false,
      "dataType": "Message",
      "description": "",
      "isReadOnly": true,
      "enumName": null,
      "isCollection": true,
      "isRelationship": true,
      "isNullable": true,
      "isUnicode": null
    },
    {
      "name": "Extensions",
      "isKey": false,
      "dataType": "Extension",
      "description": "",
      "isReadOnly": true,
      "enumName": null,
      "isCollection": true,
      "isRelationship": true,
      "isNullable": true,
      "isUnicode": null
    }
  ],
  "methods": [
    {
      "name": "Copy",
      "displayName": null,
      "prerequisites": "",
      "returnType": "MailFolder",
      "isReturnNullable": null,
      "isReturnTypeCollection": false,
      "description": "",
      "syntax": null,
      "httpSuccessResponseCode": null,
      "isFunction": false,
      "parameters": [
        {
          "name": "DestinationId",
          "dataType": "String",
          "description": "",
          "isRequired": true,
          "enumName": null,
          "isNullable": null,
          "isUnicode": false
        }
      ]
    },
    {
      "name": "Move",
      "displayName": null,
      "prerequisites": "",
      "returnType": "MailFolder",
      "isReturnNullable": null,
      "isReturnTypeCollection": false,
      "description": "",
      "syntax": null,
      "httpSuccessResponseCode": null,
      "isFunction": false,
      "parameters": [
        {
          "name": "DestinationId",
          "dataType": "String",
          "description": "",
          "isRequired": true,
          "enumName": null,
          "isNullable": null,
          "isUnicode": false
        }
      ]
    }
  ]
}